README.txt
setup.py
docs/HISTORY.txt
redturtle/__init__.py
redturtle.portletpage.views.egg-info/PKG-INFO
redturtle.portletpage.views.egg-info/SOURCES.txt
redturtle.portletpage.views.egg-info/dependency_links.txt
redturtle.portletpage.views.egg-info/entry_points.txt
redturtle.portletpage.views.egg-info/namespace_packages.txt
redturtle.portletpage.views.egg-info/not-zip-safe
redturtle.portletpage.views.egg-info/requires.txt
redturtle.portletpage.views.egg-info/top_level.txt
redturtle/portletpage/__init__.py
redturtle/portletpage/views/__init__.py
redturtle/portletpage/views/configure.zcml
redturtle/portletpage/views/i18n.sh
redturtle/portletpage/views/browser/__init__.py
redturtle/portletpage/views/browser/configure.zcml
redturtle/portletpage/views/browser/just-portlets.pt
redturtle/portletpage/views/browser/no-title.pt
redturtle/portletpage/views/browser/tabbed-zones.pt
redturtle/portletpage/views/i18n/redturtle.portletpage.views-plone-it.po
redturtle/portletpage/views/i18n/redturtle.portletpage.views-plone-manual.pot
redturtle/portletpage/views/i18n/redturtle.portletpage.views-plone.pot
redturtle/portletpage/views/profiles/default/metadata.xml
redturtle/portletpage/views/profiles/default/types.xml
redturtle/portletpage/views/profiles/default/types/Portlet_Page.xml