Metadata-Version: 1.0
Name: redturtle.portletpage.views
Version: 0.6.0
Summary: Additional views for Plone collective.portletpage product
Home-page: http://plone.org/products/redturtle.portletpage.views
Author: RedTurtle Technology
Author-email: sviluppoplone@redturtle.net
License: GPL
Keywords: portlet view portletpage
Platform: UNKNOWN
Classifier: Programming Language :: Python
Classifier: Topic :: Software Development :: Libraries :: Python Modules
